{
  "version": "0.0.1",
  "catchAll": {},
  "startNode": "entry",
  "nodes": [
    {
      "id": "d1658d1777",
      "name": "entry",
      "onEnter": [
        "say #!builtin_text-Hdf1-b"
      ],
      "onReceive": null,
      "next": [
        {
          "condition": "true",
          "node": "node-57af"
        }
      ]
    },
    {
      "id": "21c677f506",
      "name": "node-57af",
      "next": [
        {
          "condition": "true",
          "node": "#"
        }
      ],
      "onEnter": [
        "say #!builtin_text-C4vjMg",
        "say #!builtin_text-8HUuK0"
      ],
      "onReceive": null,
      "type": "standard"
    }
  ]
}